django_serialize.py
django_serialize-1.3.2.dist-info/DESCRIPTION.rst
django_serialize-1.3.2.dist-info/METADATA
django_serialize-1.3.2.dist-info/RECORD
django_serialize-1.3.2.dist-info/WHEEL
django_serialize-1.3.2.dist-info/metadata.json
django_serialize-1.3.2.dist-info/top_level.txt
