Metadata-Version: 2.0
Name: django-serialize
Version: 1.3.2
Summary: Serialization utilities for django models
Home-page: https://github.com/mirusresearch/django_serialize
Author: Mirus Research
Author-email: frank@mirusresearch.com
License: MIT, see LICENSE
Platform: UNKNOWN
Requires-Dist: packaging (>=16.8)
Requires-Dist: six (>=1.11.0)
